ry-0.0.75.dist-info/METADATA
ry-0.0.75.dist-info/WHEEL
ry-0.0.75.dist-info/licenses/LICENSE-APACHE
ry-0.0.75.dist-info/licenses/LICENSE-MIT
ry/JSON.pyi
ry/__about__.py
ry/__init__.py
ry/__main__.py
ry/_types.py
ry/dev/__init__.py
ry/dev/__main__.py
ry/dirs.pyi
ry/protocols.py
ry/py.typed
ry/ryo3.cpython-314t-i386-linux-gnu.so
ry/ryo3/JSON.pyi
ry/ryo3/__about__.pyi
ry/ryo3/__init__.pyi
ry/ryo3/_brotli.pyi
ry/ryo3/_bytes.pyi
ry/ryo3/_bzip2.pyi
ry/ryo3/_dev.pyi
ry/ryo3/_flate2.pyi
ry/ryo3/_fnv.pyi
ry/ryo3/_fspath.pyi
ry/ryo3/_glob.pyi
ry/ryo3/_globset.pyi
ry/ryo3/_heck.pyi
ry/ryo3/_http.pyi
ry/ryo3/_jiff.pyi
ry/ryo3/_jiff_tz.pyi
ry/ryo3/_jiter.pyi
ry/ryo3/_memchr.pyi
ry/ryo3/_quick_maths.pyi
ry/ryo3/_regex.pyi
ry/ryo3/_reqwest.pyi
ry/ryo3/_same_file.pyi
ry/ryo3/_shlex.pyi
ry/ryo3/_size.pyi
ry/ryo3/_sqlformat.pyi
ry/ryo3/_std.pyi
ry/ryo3/_std_constants.pyi
ry/ryo3/_tokio.pyi
ry/ryo3/_unindent.pyi
ry/ryo3/_url.pyi
ry/ryo3/_walkdir.pyi
ry/ryo3/_which.pyi
ry/ryo3/_zstd.pyi
ry/ryo3/dirs.pyi
ry/ryo3/errors.pyi
ry/ryo3/orjson.pyi
ry/ryo3/sh.pyi
ry/ryo3/ulid.pyi
ry/ryo3/uuid.pyi
ry/ryo3/xxhash.pyi
ry/ryo3/zstd.pyi
ry/ulid.pyi
ry/uuid.pyi
ry/xxhash.pyi
ry/zstd.pyi
ry-0.0.75.dist-info/RECORD
