Metadata-Version: 2.4
Name: ry
Version: 0.0.75
Classifier: Development Status :: 4 - Beta
Classifier: Intended Audience :: Developers
Classifier: License :: OSI Approved :: Apache Software License
Classifier: License :: OSI Approved :: MIT License
Classifier: Programming Language :: Python
Classifier: Programming Language :: Python :: 3 :: Only
Classifier: Programming Language :: Python :: 3.11
Classifier: Programming Language :: Python :: 3.12
Classifier: Programming Language :: Python :: 3.13
Classifier: Programming Language :: Python :: 3.14
Classifier: Programming Language :: Python :: Implementation :: CPython
Classifier: Programming Language :: Python :: Implementation :: PyPy
Classifier: Programming Language :: Rust
Classifier: Topic :: Utilities
Classifier: Typing :: Typed
License-File: LICENSE-APACHE
License-File: LICENSE-MIT
Summary: ry = rust + python
Keywords: datetime,http,jiff,json,pyo3,reqwest,rust,tokio,xxhash,zstd
Home-Page: https://github.com/jessekrubin/ry
Author-email: jesse rubin <jessekrubin@gmail.com>
Maintainer-email: jesse rubin <jessekrubin@gmail.com>
License-Expression: MIT OR Apache-2.0
Requires-Python: >=3.11
Project-URL: Changelog, https://github.com/jessekrubin/ry/blob/main/CHANGELOG.md
Project-URL: Homepage, https://github.com/jessekrubin/ry
Project-URL: Issues, https://github.com/jessekrubin/ry/issues
Project-URL: Source, https://github.com/jessekrubin/ry
